llm_azure_ai_foundry.py
llm_azure_ai_foundry-0.3.1.dist-info/licenses/LICENSE
llm_azure_ai_foundry-0.3.1.dist-info/METADATA
llm_azure_ai_foundry-0.3.1.dist-info/WHEEL
llm_azure_ai_foundry-0.3.1.dist-info/entry_points.txt
llm_azure_ai_foundry-0.3.1.dist-info/top_level.txt
llm_azure_ai_foundry-0.3.1.dist-info/RECORD
