Metadata-Version: 2.4
Name: llm-azure-ai-foundry
Version: 0.3.1
Summary: LLM plugin to access model deployments on Azure AI Foundry and Foundry Local
Author: Anthony Shaw
License: MIT
Project-URL: Homepage, https://github.com/tonybaloney/llm-azure-ai-foundry
Project-URL: Changelog, https://github.com/tonybaloney/llm-azure-ai-foundry/releases
Project-URL: Issues, https://github.com/tonybaloney/llm-azure-ai-foundry/issues
Project-URL: CI, https://github.com/tonybaloney/llm-azure-ai-foundry/actions
Classifier: License :: OSI Approved :: MIT License
License-File: LICENSE
Requires-Dist: aiohttp>=3.11.18
Requires-Dist: llm>=0.26
Requires-Dist: azure-ai-projects<2.0.0,>=1.0.0
Requires-Dist: azure-identity
Requires-Dist: foundry-local-sdk==0.3.1
Provides-Extra: test
Requires-Dist: pytest; extra == "test"
Requires-Dist: pytest-recording; extra == "test"
Requires-Dist: pytest-asyncio; extra == "test"
Requires-Dist: ruff; extra == "test"
Requires-Dist: pyright; extra == "test"
Dynamic: license-file
